{
  "proxy_count": 586095,
  "alive_count": 107,
  "elite_count": 107,
  "google_pass_count": 32,
  "hijacked_count": 212826,
  "avg_latency_ms": 1844,
  "avg_reliability_pct": 1.2,
  "by_protocol": [
    {
      "protocol": "http",
      "proxy_count": 64
    },
    {
      "protocol": "socks4",
      "proxy_count": 13
    },
    {
      "protocol": "socks5",
      "proxy_count": 30
    }
  ],
  "last_updated": 1784355284,
  "source_quality": [
    {
      "source": "proxyscrape",
      "total": 6561,
      "alive": 55,
      "elite": 55,
      "google_pass": 25,
      "avg_latency_ms": 2221.018181818182,
      "alive_pct": 0.8
    },
    {
      "source": "geonode",
      "total": 385,
      "alive": 3,
      "elite": 3,
      "google_pass": 0,
      "avg_latency_ms": 1848,
      "alive_pct": 0.8
    },
    {
      "source": "r00tee",
      "total": 7550,
      "alive": 15,
      "elite": 15,
      "google_pass": 1,
      "avg_latency_ms": 1811.2,
      "alive_pct": 0.2
    },
    {
      "source": "iplocate",
      "total": 2879,
      "alive": 7,
      "elite": 7,
      "google_pass": 2,
      "avg_latency_ms": 935.8571428571429,
      "alive_pct": 0.2
    },
    {
      "source": "clearproxy",
      "total": 470,
      "alive": 1,
      "elite": 1,
      "google_pass": 0,
      "avg_latency_ms": 162,
      "alive_pct": 0.2
    },
    {
      "source": "thespeedx",
      "total": 4074,
      "alive": 3,
      "elite": 3,
      "google_pass": 1,
      "avg_latency_ms": 2031,
      "alive_pct": 0.1
    },
    {
      "source": "proxifly",
      "total": 2890,
      "alive": 2,
      "elite": 2,
      "google_pass": 0,
      "avg_latency_ms": 1524,
      "alive_pct": 0.1
    },
    {
      "source": "zloi",
      "total": 4313,
      "alive": 1,
      "elite": 1,
      "google_pass": 0,
      "avg_latency_ms": 2714,
      "alive_pct": 0
    },
    {
      "source": "zevtyardt",
      "total": 1,
      "alive": 0,
      "elite": 0,
      "google_pass": 0,
      "avg_latency_ms": null,
      "alive_pct": 0
    },
    {
      "source": "vmheaven",
      "total": 6132,
      "alive": 3,
      "elite": 3,
      "google_pass": 0,
      "avg_latency_ms": 884.3333333333334,
      "alive_pct": 0
    },
    {
      "source": "vanndev",
      "total": 59,
      "alive": 0,
      "elite": 0,
      "google_pass": 0,
      "avg_latency_ms": null,
      "alive_pct": 0
    },
    {
      "source": "vakhov",
      "total": 3,
      "alive": 0,
      "elite": 0,
      "google_pass": 0,
      "avg_latency_ms": null,
      "alive_pct": 0
    },
    {
      "source": "sunny9577",
      "total": 284,
      "alive": 0,
      "elite": 0,
      "google_pass": 0,
      "avg_latency_ms": null,
      "alive_pct": 0
    },
    {
      "source": "spysme",
      "total": 168,
      "alive": 0,
      "elite": 0,
      "google_pass": 0,
      "avg_latency_ms": null,
      "alive_pct": 0
    },
    {
      "source": "scanner",
      "total": 154094,
      "alive": 2,
      "elite": 2,
      "google_pass": 0,
      "avg_latency_ms": 3162.5,
      "alive_pct": 0
    },
    {
      "source": "roosterkid",
      "total": 3,
      "alive": 0,
      "elite": 0,
      "google_pass": 0,
      "avg_latency_ms": null,
      "alive_pct": 0
    },
    {
      "source": "prxchk",
      "total": 35,
      "alive": 0,
      "elite": 0,
      "google_pass": 0,
      "avg_latency_ms": null,
      "alive_pct": 0
    },
    {
      "source": "proxyscraper-gh",
      "total": 8,
      "alive": 0,
      "elite": 0,
      "google_pass": 0,
      "avg_latency_ms": null,
      "alive_pct": 0
    },
    {
      "source": "proxyscrape-country",
      "total": 2,
      "alive": 0,
      "elite": 0,
      "google_pass": 0,
      "avg_latency_ms": null,
      "alive_pct": 0
    },
    {
      "source": "murongpig",
      "total": 219,
      "alive": 0,
      "elite": 0,
      "google_pass": 0,
      "avg_latency_ms": null,
      "alive_pct": 0
    },
    {
      "source": "monosans",
      "total": 59,
      "alive": 0,
      "elite": 0,
      "google_pass": 0,
      "avg_latency_ms": null,
      "alive_pct": 0
    },
    {
      "source": "mmpx12",
      "total": 2,
      "alive": 0,
      "elite": 0,
      "google_pass": 0,
      "avg_latency_ms": null,
      "alive_pct": 0
    },
    {
      "source": "hookzof",
      "total": 43,
      "alive": 0,
      "elite": 0,
      "google_pass": 0,
      "avg_latency_ms": null,
      "alive_pct": 0
    },
    {
      "source": "gh:tuanminpay",
      "total": 2329,
      "alive": 0,
      "elite": 0,
      "google_pass": 0,
      "avg_latency_ms": null,
      "alive_pct": 0
    },
    {
      "source": "gh:trio666",
      "total": 638,
      "alive": 0,
      "elite": 0,
      "google_pass": 0,
      "avg_latency_ms": null,
      "alive_pct": 0
    },
    {
      "source": "gh:skiddle",
      "total": 796,
      "alive": 0,
      "elite": 0,
      "google_pass": 0,
      "avg_latency_ms": null,
      "alive_pct": 0
    },
    {
      "source": "gh:proxygenerator",
      "total": 1748,
      "alive": 0,
      "elite": 0,
      "google_pass": 0,
      "avg_latency_ms": null,
      "alive_pct": 0
    },
    {
      "source": "gh:openproxyhub",
      "total": 435,
      "alive": 0,
      "elite": 0,
      "google_pass": 0,
      "avg_latency_ms": null,
      "alive_pct": 0
    },
    {
      "source": "gh:officialputuid",
      "total": 2551,
      "alive": 0,
      "elite": 0,
      "google_pass": 0,
      "avg_latency_ms": null,
      "alive_pct": 0
    },
    {
      "source": "gh:munachukwuw",
      "total": 415,
      "alive": 0,
      "elite": 0,
      "google_pass": 0,
      "avg_latency_ms": null,
      "alive_pct": 0
    },
    {
      "source": "gh:komutan234",
      "total": 2256,
      "alive": 0,
      "elite": 0,
      "google_pass": 0,
      "avg_latency_ms": null,
      "alive_pct": 0
    },
    {
      "source": "gh:itsanwar",
      "total": 2153,
      "alive": 0,
      "elite": 0,
      "google_pass": 0,
      "avg_latency_ms": null,
      "alive_pct": 0
    },
    {
      "source": "gh:gitrecon1455",
      "total": 278293,
      "alive": 5,
      "elite": 5,
      "google_pass": 2,
      "avg_latency_ms": 1088,
      "alive_pct": 0
    },
    {
      "source": "gh:ebrasha",
      "total": 1362,
      "alive": 0,
      "elite": 0,
      "google_pass": 0,
      "avg_latency_ms": null,
      "alive_pct": 0
    },
    {
      "source": "gh:dpangestuw",
      "total": 8338,
      "alive": 1,
      "elite": 1,
      "google_pass": 0,
      "avg_latency_ms": 1131,
      "alive_pct": 0
    },
    {
      "source": "gh:anonym0us",
      "total": 1875,
      "alive": 0,
      "elite": 0,
      "google_pass": 0,
      "avg_latency_ms": null,
      "alive_pct": 0
    },
    {
      "source": "gh:alphaa1111",
      "total": 43,
      "alive": 0,
      "elite": 0,
      "google_pass": 0,
      "avg_latency_ms": null,
      "alive_pct": 0
    },
    {
      "source": "geonode-country",
      "total": 5,
      "alive": 0,
      "elite": 0,
      "google_pass": 0,
      "avg_latency_ms": null,
      "alive_pct": 0
    },
    {
      "source": "freeproxylist",
      "total": 134,
      "alive": 0,
      "elite": 0,
      "google_pass": 0,
      "avg_latency_ms": null,
      "alive_pct": 0
    },
    {
      "source": "fate0",
      "total": 193,
      "alive": 0,
      "elite": 0,
      "google_pass": 0,
      "avg_latency_ms": null,
      "alive_pct": 0
    },
    {
      "source": "ercin",
      "total": 25142,
      "alive": 5,
      "elite": 5,
      "google_pass": 1,
      "avg_latency_ms": 1503.8,
      "alive_pct": 0
    },
    {
      "source": "dinoz0rg",
      "total": 3461,
      "alive": 0,
      "elite": 0,
      "google_pass": 0,
      "avg_latency_ms": null,
      "alive_pct": 0
    },
    {
      "source": "databay-country",
      "total": 48,
      "alive": 0,
      "elite": 0,
      "google_pass": 0,
      "avg_latency_ms": null,
      "alive_pct": 0
    },
    {
      "source": "databay",
      "total": 1289,
      "alive": 0,
      "elite": 0,
      "google_pass": 0,
      "avg_latency_ms": null,
      "alive_pct": 0
    },
    {
      "source": "casa",
      "total": 58932,
      "alive": 4,
      "elite": 4,
      "google_pass": 0,
      "avg_latency_ms": 209.5,
      "alive_pct": 0
    },
    {
      "source": "acidvegas",
      "total": 3425,
      "alive": 0,
      "elite": 0,
      "google_pass": 0,
      "avg_latency_ms": null,
      "alive_pct": 0
    }
  ]
}