{
  "proxy_count": 586199,
  "alive_count": 68,
  "elite_count": 68,
  "google_pass_count": 37,
  "hijacked_count": 213640,
  "avg_latency_ms": 2662,
  "avg_reliability_pct": 1.2,
  "by_protocol": [
    {
      "protocol": "http",
      "proxy_count": 42
    },
    {
      "protocol": "socks5",
      "proxy_count": 26
    }
  ],
  "last_updated": 1784362012,
  "source_quality": [
    {
      "source": "proxyscrape",
      "total": 6773,
      "alive": 40,
      "elite": 40,
      "google_pass": 29,
      "avg_latency_ms": 3596.925,
      "alive_pct": 0.6
    },
    {
      "source": "iplocate",
      "total": 2696,
      "alive": 6,
      "elite": 6,
      "google_pass": 1,
      "avg_latency_ms": 919.5,
      "alive_pct": 0.2
    },
    {
      "source": "thespeedx",
      "total": 3592,
      "alive": 5,
      "elite": 5,
      "google_pass": 3,
      "avg_latency_ms": 2076.8,
      "alive_pct": 0.1
    },
    {
      "source": "zloi",
      "total": 4360,
      "alive": 1,
      "elite": 1,
      "google_pass": 1,
      "avg_latency_ms": 1137,
      "alive_pct": 0
    },
    {
      "source": "zevtyardt",
      "total": 1,
      "alive": 0,
      "elite": 0,
      "google_pass": 0,
      "avg_latency_ms": null,
      "alive_pct": 0
    },
    {
      "source": "vmheaven",
      "total": 6257,
      "alive": 0,
      "elite": 0,
      "google_pass": 0,
      "avg_latency_ms": null,
      "alive_pct": 0
    },
    {
      "source": "vanndev",
      "total": 49,
      "alive": 0,
      "elite": 0,
      "google_pass": 0,
      "avg_latency_ms": null,
      "alive_pct": 0
    },
    {
      "source": "vakhov",
      "total": 3,
      "alive": 0,
      "elite": 0,
      "google_pass": 0,
      "avg_latency_ms": null,
      "alive_pct": 0
    },
    {
      "source": "sunny9577",
      "total": 389,
      "alive": 0,
      "elite": 0,
      "google_pass": 0,
      "avg_latency_ms": null,
      "alive_pct": 0
    },
    {
      "source": "spysme",
      "total": 173,
      "alive": 0,
      "elite": 0,
      "google_pass": 0,
      "avg_latency_ms": null,
      "alive_pct": 0
    },
    {
      "source": "scanner",
      "total": 154090,
      "alive": 2,
      "elite": 2,
      "google_pass": 0,
      "avg_latency_ms": 2297.5,
      "alive_pct": 0
    },
    {
      "source": "roosterkid",
      "total": 3,
      "alive": 0,
      "elite": 0,
      "google_pass": 0,
      "avg_latency_ms": null,
      "alive_pct": 0
    },
    {
      "source": "r00tee",
      "total": 7679,
      "alive": 2,
      "elite": 2,
      "google_pass": 2,
      "avg_latency_ms": 1845.5,
      "alive_pct": 0
    },
    {
      "source": "prxchk",
      "total": 35,
      "alive": 0,
      "elite": 0,
      "google_pass": 0,
      "avg_latency_ms": null,
      "alive_pct": 0
    },
    {
      "source": "proxyscraper-gh",
      "total": 8,
      "alive": 0,
      "elite": 0,
      "google_pass": 0,
      "avg_latency_ms": null,
      "alive_pct": 0
    },
    {
      "source": "proxyscrape-country",
      "total": 2,
      "alive": 0,
      "elite": 0,
      "google_pass": 0,
      "avg_latency_ms": null,
      "alive_pct": 0
    },
    {
      "source": "proxifly",
      "total": 2948,
      "alive": 1,
      "elite": 1,
      "google_pass": 1,
      "avg_latency_ms": 1249,
      "alive_pct": 0
    },
    {
      "source": "murongpig",
      "total": 219,
      "alive": 0,
      "elite": 0,
      "google_pass": 0,
      "avg_latency_ms": null,
      "alive_pct": 0
    },
    {
      "source": "monosans",
      "total": 45,
      "alive": 0,
      "elite": 0,
      "google_pass": 0,
      "avg_latency_ms": null,
      "alive_pct": 0
    },
    {
      "source": "mmpx12",
      "total": 2,
      "alive": 0,
      "elite": 0,
      "google_pass": 0,
      "avg_latency_ms": null,
      "alive_pct": 0
    },
    {
      "source": "hookzof",
      "total": 43,
      "alive": 0,
      "elite": 0,
      "google_pass": 0,
      "avg_latency_ms": null,
      "alive_pct": 0
    },
    {
      "source": "gh:tuanminpay",
      "total": 2106,
      "alive": 0,
      "elite": 0,
      "google_pass": 0,
      "avg_latency_ms": null,
      "alive_pct": 0
    },
    {
      "source": "gh:trio666",
      "total": 640,
      "alive": 0,
      "elite": 0,
      "google_pass": 0,
      "avg_latency_ms": null,
      "alive_pct": 0
    },
    {
      "source": "gh:skiddle",
      "total": 794,
      "alive": 0,
      "elite": 0,
      "google_pass": 0,
      "avg_latency_ms": null,
      "alive_pct": 0
    },
    {
      "source": "gh:proxygenerator",
      "total": 1750,
      "alive": 0,
      "elite": 0,
      "google_pass": 0,
      "avg_latency_ms": null,
      "alive_pct": 0
    },
    {
      "source": "gh:openproxyhub",
      "total": 435,
      "alive": 0,
      "elite": 0,
      "google_pass": 0,
      "avg_latency_ms": null,
      "alive_pct": 0
    },
    {
      "source": "gh:officialputuid",
      "total": 2529,
      "alive": 0,
      "elite": 0,
      "google_pass": 0,
      "avg_latency_ms": null,
      "alive_pct": 0
    },
    {
      "source": "gh:munachukwuw",
      "total": 415,
      "alive": 0,
      "elite": 0,
      "google_pass": 0,
      "avg_latency_ms": null,
      "alive_pct": 0
    },
    {
      "source": "gh:komutan234",
      "total": 2245,
      "alive": 0,
      "elite": 0,
      "google_pass": 0,
      "avg_latency_ms": null,
      "alive_pct": 0
    },
    {
      "source": "gh:itsanwar",
      "total": 2126,
      "alive": 0,
      "elite": 0,
      "google_pass": 0,
      "avg_latency_ms": null,
      "alive_pct": 0
    },
    {
      "source": "gh:gitrecon1455",
      "total": 278230,
      "alive": 2,
      "elite": 2,
      "google_pass": 0,
      "avg_latency_ms": 175,
      "alive_pct": 0
    },
    {
      "source": "gh:ebrasha",
      "total": 1474,
      "alive": 0,
      "elite": 0,
      "google_pass": 0,
      "avg_latency_ms": null,
      "alive_pct": 0
    },
    {
      "source": "gh:dpangestuw",
      "total": 8340,
      "alive": 0,
      "elite": 0,
      "google_pass": 0,
      "avg_latency_ms": null,
      "alive_pct": 0
    },
    {
      "source": "gh:anonym0us",
      "total": 2005,
      "alive": 0,
      "elite": 0,
      "google_pass": 0,
      "avg_latency_ms": null,
      "alive_pct": 0
    },
    {
      "source": "gh:alphaa1111",
      "total": 48,
      "alive": 0,
      "elite": 0,
      "google_pass": 0,
      "avg_latency_ms": null,
      "alive_pct": 0
    },
    {
      "source": "geonode-country",
      "total": 5,
      "alive": 0,
      "elite": 0,
      "google_pass": 0,
      "avg_latency_ms": null,
      "alive_pct": 0
    },
    {
      "source": "geonode",
      "total": 391,
      "alive": 0,
      "elite": 0,
      "google_pass": 0,
      "avg_latency_ms": null,
      "alive_pct": 0
    },
    {
      "source": "freeproxylist",
      "total": 136,
      "alive": 0,
      "elite": 0,
      "google_pass": 0,
      "avg_latency_ms": null,
      "alive_pct": 0
    },
    {
      "source": "fate0",
      "total": 193,
      "alive": 0,
      "elite": 0,
      "google_pass": 0,
      "avg_latency_ms": null,
      "alive_pct": 0
    },
    {
      "source": "ercin",
      "total": 25497,
      "alive": 2,
      "elite": 2,
      "google_pass": 0,
      "avg_latency_ms": 2507.5,
      "alive_pct": 0
    },
    {
      "source": "dinoz0rg",
      "total": 3369,
      "alive": 0,
      "elite": 0,
      "google_pass": 0,
      "avg_latency_ms": null,
      "alive_pct": 0
    },
    {
      "source": "databay-country",
      "total": 51,
      "alive": 0,
      "elite": 0,
      "google_pass": 0,
      "avg_latency_ms": null,
      "alive_pct": 0
    },
    {
      "source": "databay",
      "total": 1241,
      "alive": 0,
      "elite": 0,
      "google_pass": 0,
      "avg_latency_ms": null,
      "alive_pct": 0
    },
    {
      "source": "clearproxy",
      "total": 470,
      "alive": 0,
      "elite": 0,
      "google_pass": 0,
      "avg_latency_ms": null,
      "alive_pct": 0
    },
    {
      "source": "casa",
      "total": 58907,
      "alive": 6,
      "elite": 6,
      "google_pass": 0,
      "avg_latency_ms": 305.8333333333333,
      "alive_pct": 0
    },
    {
      "source": "acidvegas",
      "total": 3435,
      "alive": 1,
      "elite": 1,
      "google_pass": 0,
      "avg_latency_ms": 3365,
      "alive_pct": 0
    }
  ]
}