{
  "proxy_count": 566273,
  "alive_count": 217,
  "elite_count": 217,
  "google_pass_count": 149,
  "hijacked_count": 212454,
  "avg_latency_ms": 3014,
  "avg_reliability_pct": 1.1,
  "by_protocol": [
    {
      "protocol": "http",
      "proxy_count": 71
    },
    {
      "protocol": "socks4",
      "proxy_count": 9
    },
    {
      "protocol": "socks5",
      "proxy_count": 137
    }
  ],
  "last_updated": 1783842894,
  "source_quality": [
    {
      "source": "proxyscrape",
      "total": 12221,
      "alive": 139,
      "elite": 139,
      "google_pass": 109,
      "avg_latency_ms": 3282.73381294964,
      "alive_pct": 1.1
    },
    {
      "source": "spysme",
      "total": 117,
      "alive": 1,
      "elite": 1,
      "google_pass": 0,
      "avg_latency_ms": 899,
      "alive_pct": 0.9
    },
    {
      "source": "murongpig",
      "total": 217,
      "alive": 2,
      "elite": 2,
      "google_pass": 1,
      "avg_latency_ms": 1438,
      "alive_pct": 0.9
    },
    {
      "source": "geonode",
      "total": 417,
      "alive": 2,
      "elite": 2,
      "google_pass": 1,
      "avg_latency_ms": 2120,
      "alive_pct": 0.5
    },
    {
      "source": "freeproxylist",
      "total": 187,
      "alive": 1,
      "elite": 1,
      "google_pass": 0,
      "avg_latency_ms": 787,
      "alive_pct": 0.5
    },
    {
      "source": "sunny9577",
      "total": 376,
      "alive": 1,
      "elite": 1,
      "google_pass": 0,
      "avg_latency_ms": 1078,
      "alive_pct": 0.3
    },
    {
      "source": "thespeedx",
      "total": 5947,
      "alive": 13,
      "elite": 13,
      "google_pass": 6,
      "avg_latency_ms": 2702.153846153846,
      "alive_pct": 0.2
    },
    {
      "source": "iplocate",
      "total": 3378,
      "alive": 7,
      "elite": 7,
      "google_pass": 1,
      "avg_latency_ms": 631.7142857142857,
      "alive_pct": 0.2
    },
    {
      "source": "acidvegas",
      "total": 5145,
      "alive": 8,
      "elite": 8,
      "google_pass": 6,
      "avg_latency_ms": 3322.875,
      "alive_pct": 0.2
    },
    {
      "source": "vmheaven",
      "total": 5600,
      "alive": 3,
      "elite": 3,
      "google_pass": 1,
      "avg_latency_ms": 1913.3333333333333,
      "alive_pct": 0.1
    },
    {
      "source": "proxifly",
      "total": 3531,
      "alive": 4,
      "elite": 4,
      "google_pass": 2,
      "avg_latency_ms": 2008,
      "alive_pct": 0.1
    },
    {
      "source": "gh:proxygenerator",
      "total": 1727,
      "alive": 2,
      "elite": 2,
      "google_pass": 0,
      "avg_latency_ms": 1128,
      "alive_pct": 0.1
    },
    {
      "source": "gh:dpangestuw",
      "total": 1998,
      "alive": 2,
      "elite": 2,
      "google_pass": 2,
      "avg_latency_ms": 5984.5,
      "alive_pct": 0.1
    },
    {
      "source": "ercin",
      "total": 29790,
      "alive": 18,
      "elite": 18,
      "google_pass": 17,
      "avg_latency_ms": 3514.1666666666665,
      "alive_pct": 0.1
    },
    {
      "source": "databay",
      "total": 1379,
      "alive": 1,
      "elite": 1,
      "google_pass": 0,
      "avg_latency_ms": 703,
      "alive_pct": 0.1
    },
    {
      "source": "zloi",
      "total": 3425,
      "alive": 1,
      "elite": 1,
      "google_pass": 1,
      "avg_latency_ms": 5342,
      "alive_pct": 0
    },
    {
      "source": "zevtyardt",
      "total": 4,
      "alive": 0,
      "elite": 0,
      "google_pass": 0,
      "avg_latency_ms": null,
      "alive_pct": 0
    },
    {
      "source": "vanndev",
      "total": 29,
      "alive": 0,
      "elite": 0,
      "google_pass": 0,
      "avg_latency_ms": null,
      "alive_pct": 0
    },
    {
      "source": "vakhov",
      "total": 3,
      "alive": 0,
      "elite": 0,
      "google_pass": 0,
      "avg_latency_ms": null,
      "alive_pct": 0
    },
    {
      "source": "scanner",
      "total": 154007,
      "alive": 2,
      "elite": 2,
      "google_pass": 0,
      "avg_latency_ms": 2661,
      "alive_pct": 0
    },
    {
      "source": "roosterkid",
      "total": 6,
      "alive": 0,
      "elite": 0,
      "google_pass": 0,
      "avg_latency_ms": null,
      "alive_pct": 0
    },
    {
      "source": "r00tee",
      "total": 7603,
      "alive": 2,
      "elite": 2,
      "google_pass": 1,
      "avg_latency_ms": 2429,
      "alive_pct": 0
    },
    {
      "source": "prxchk",
      "total": 35,
      "alive": 0,
      "elite": 0,
      "google_pass": 0,
      "avg_latency_ms": null,
      "alive_pct": 0
    },
    {
      "source": "proxyscraper-gh",
      "total": 10,
      "alive": 0,
      "elite": 0,
      "google_pass": 0,
      "avg_latency_ms": null,
      "alive_pct": 0
    },
    {
      "source": "proxyscrape-country",
      "total": 6,
      "alive": 0,
      "elite": 0,
      "google_pass": 0,
      "avg_latency_ms": null,
      "alive_pct": 0
    },
    {
      "source": "monosans",
      "total": 54,
      "alive": 0,
      "elite": 0,
      "google_pass": 0,
      "avg_latency_ms": null,
      "alive_pct": 0
    },
    {
      "source": "mmpx12",
      "total": 2,
      "alive": 0,
      "elite": 0,
      "google_pass": 0,
      "avg_latency_ms": null,
      "alive_pct": 0
    },
    {
      "source": "hookzof",
      "total": 48,
      "alive": 0,
      "elite": 0,
      "google_pass": 0,
      "avg_latency_ms": null,
      "alive_pct": 0
    },
    {
      "source": "gh:tuanminpay",
      "total": 2523,
      "alive": 1,
      "elite": 1,
      "google_pass": 0,
      "avg_latency_ms": 417,
      "alive_pct": 0
    },
    {
      "source": "gh:trio666",
      "total": 715,
      "alive": 0,
      "elite": 0,
      "google_pass": 0,
      "avg_latency_ms": null,
      "alive_pct": 0
    },
    {
      "source": "gh:skiddle",
      "total": 779,
      "alive": 0,
      "elite": 0,
      "google_pass": 0,
      "avg_latency_ms": null,
      "alive_pct": 0
    },
    {
      "source": "gh:openproxyhub",
      "total": 435,
      "alive": 0,
      "elite": 0,
      "google_pass": 0,
      "avg_latency_ms": null,
      "alive_pct": 0
    },
    {
      "source": "gh:officialputuid",
      "total": 2161,
      "alive": 0,
      "elite": 0,
      "google_pass": 0,
      "avg_latency_ms": null,
      "alive_pct": 0
    },
    {
      "source": "gh:munachukwuw",
      "total": 415,
      "alive": 0,
      "elite": 0,
      "google_pass": 0,
      "avg_latency_ms": null,
      "alive_pct": 0
    },
    {
      "source": "gh:komutan234",
      "total": 2029,
      "alive": 0,
      "elite": 0,
      "google_pass": 0,
      "avg_latency_ms": null,
      "alive_pct": 0
    },
    {
      "source": "gh:itsanwar",
      "total": 2009,
      "alive": 1,
      "elite": 1,
      "google_pass": 0,
      "avg_latency_ms": 4728,
      "alive_pct": 0
    },
    {
      "source": "gh:gitrecon1455",
      "total": 253160,
      "alive": 3,
      "elite": 3,
      "google_pass": 0,
      "avg_latency_ms": 2464,
      "alive_pct": 0
    },
    {
      "source": "gh:ebrasha",
      "total": 1041,
      "alive": 0,
      "elite": 0,
      "google_pass": 0,
      "avg_latency_ms": null,
      "alive_pct": 0
    },
    {
      "source": "gh:anonym0us",
      "total": 1929,
      "alive": 0,
      "elite": 0,
      "google_pass": 0,
      "avg_latency_ms": null,
      "alive_pct": 0
    },
    {
      "source": "gh:alphaa1111",
      "total": 29,
      "alive": 0,
      "elite": 0,
      "google_pass": 0,
      "avg_latency_ms": null,
      "alive_pct": 0
    },
    {
      "source": "geonode-country",
      "total": 4,
      "alive": 0,
      "elite": 0,
      "google_pass": 0,
      "avg_latency_ms": null,
      "alive_pct": 0
    },
    {
      "source": "fate0",
      "total": 193,
      "alive": 0,
      "elite": 0,
      "google_pass": 0,
      "avg_latency_ms": null,
      "alive_pct": 0
    },
    {
      "source": "dinoz0rg",
      "total": 2627,
      "alive": 0,
      "elite": 0,
      "google_pass": 0,
      "avg_latency_ms": null,
      "alive_pct": 0
    },
    {
      "source": "databay-country",
      "total": 60,
      "alive": 0,
      "elite": 0,
      "google_pass": 0,
      "avg_latency_ms": null,
      "alive_pct": 0
    },
    {
      "source": "clearproxy",
      "total": 451,
      "alive": 0,
      "elite": 0,
      "google_pass": 0,
      "avg_latency_ms": null,
      "alive_pct": 0
    },
    {
      "source": "casa",
      "total": 58451,
      "alive": 3,
      "elite": 3,
      "google_pass": 1,
      "avg_latency_ms": 565.6666666666666,
      "alive_pct": 0
    }
  ]
}